typed_graphql/__init__.py
typed_graphql/core.py
typed_graphql/core.py~
typed_graphql/execute.py
typed_graphql/py.typed
typed_graphql/scalars.py
typed_graphql/util.py
typed_graphql-0.48.0.dist-info/LICENSE
typed_graphql-0.48.0.dist-info/METADATA
typed_graphql-0.48.0.dist-info/WHEEL
typed_graphql-0.48.0.dist-info/RECORD
